{
  "announcements": [
    {
      "title": "title 1",
      "description": "description 1",
      "announcementDate": 1751878012,
      "applicationDeadline": 1751878012,
      "imageUrl": "imageUrl 1",
      "link": "link 1",
      "eligibleInstitution": [],
      "projectDuration": "projectDuration 1",
      "budgetSupport": "budgetSupport 1",
      "applicationLanguage": "applicationLanguage 1",
      "sectors": [],
      "id": "1"
    },
    {
      "title": "title 2",
      "description": "description 2",
      "announcementDate": 1751877952,
      "applicationDeadline": 1751877952,
      "imageUrl": "imageUrl 2",
      "link": "link 2",
      "eligibleInstitution": [],
      "projectDuration": "projectDuration 2",
      "budgetSupport": "budgetSupport 2",
      "applicationLanguage": "applicationLanguage 2",
      "sectors": [],
      "id": "2"
    },
    {
      "title": "title 3",
      "description": "description 3",
      "announcementDate": 1751877892,
      "applicationDeadline": 1751877892,
      "imageUrl": "imageUrl 3",
      "link": "link 3",
      "eligibleInstitution": [],
      "projectDuration": "projectDuration 3",
      "budgetSupport": "budgetSupport 3",
      "applicationLanguage": "applicationLanguage 3",
      "sectors": [],
      "id": "3"
    },
    {
      "title": "title 4",
      "description": "description 4",
      "announcementDate": 1751877832,
      "applicationDeadline": 1751877832,
      "imageUrl": "imageUrl 4",
      "link": "link 4",
      "eligibleInstitution": [],
      "projectDuration": "projectDuration 4",
      "budgetSupport": "budgetSupport 4",
      "applicationLanguage": "applicationLanguage 4",
      "sectors": [],
      "id": "4"
    },
    {
      "title": "title 5",
      "description": "description 5",
      "announcementDate": 1751877772,
      "applicationDeadline": 1751877772,
      "imageUrl": "imageUrl 5",
      "link": "link 5",
      "eligibleInstitution": [],
      "projectDuration": "projectDuration 5",
      "budgetSupport": "budgetSupport 5",
      "applicationLanguage": "applicationLanguage 5",
      "sectors": [],
      "id": "5"
    },
    {
      "title": "title 6",
      "description": "description 6",
      "announcementDate": 1751877712,
      "applicationDeadline": 1751877712,
      "imageUrl": "imageUrl 6",
      "link": "link 6",
      "eligibleInstitution": [],
      "projectDuration": "projectDuration 6",
      "budgetSupport": "budgetSupport 6",
      "applicationLanguage": "applicationLanguage 6",
      "sectors": [],
      "id": "6"
    },
    {
      "title": "title 7",
      "description": "description 7",
      "announcementDate": 1751877743,
      "applicationDeadline": 1751877743,
      "imageUrl": "imageUrl 7",
      "link": "link 7",
      "eligibleInstitution": [],
      "projectDuration": "projectDuration 7",
      "budgetSupport": "budgetSupport 7",
      "applicationLanguage": "applicationLanguage 7",
      "sectors": [],
      "id": "7"
    },
    {
      "title": "title 8",
      "description": "description 8",
      "announcementDate": 1751877683,
      "applicationDeadline": 1751877683,
      "imageUrl": "imageUrl 8",
      "link": "link 8",
      "eligibleInstitution": [],
      "projectDuration": "projectDuration 8",
      "budgetSupport": "budgetSupport 8",
      "applicationLanguage": "applicationLanguage 8",
      "sectors": [],
      "id": "8"
    }
  ]
}
